mypackage/__init__.py
mypackage/gibbs.py
mypackage/gibby_run.py
gibby_motifFinding-0.1.dist-info/METADATA
gibby_motifFinding-0.1.dist-info/WHEEL
gibby_motifFinding-0.1.dist-info/entry_points.txt
gibby_motifFinding-0.1.dist-info/top_level.txt
gibby_motifFinding-0.1.dist-info/RECORD
