Metadata-Version: 2.1
Name: gibby-motifFinding
Version: 0.1
Summary: Process genomic data to extract peak sequences and compute PWMs.
Home-page: https://github.com/yourusername/CSE_185_FinalProject
Author: Your Name
Author-email: your.email@example.com
Classifier: Programming Language :: Python :: 3
Classifier: License :: OSI Approved :: MIT License
Classifier: Operating System :: OS Independent
Requires-Python: >=3.6
Requires-Dist: biopython
Requires-Dist: numpy
Requires-Dist: seqlogo
